ssbpp
