Metadata-Version: 1.0
Name: ssbpp
Version: 1.1.5
Summary: SSBPP: A Real-time Strain Submission and Monitoring Platform for Epidemic Prevention Based on Phylogenetic Placement 
Home-page: UNKNOWN
Author: Hang Yang
Author-email: 1090692248@qq.com
License: MIT
Keywords: ssbpp
Platform: UNKNOWN
